pytest_doctest_only/__init__.py
pytest_doctest_only/plugin.py
pytest_doctest_only-0.1.2.dist-info/licenses/LICENSE
pytest_doctest_only-0.1.2.dist-info/METADATA
pytest_doctest_only-0.1.2.dist-info/WHEEL
pytest_doctest_only-0.1.2.dist-info/entry_points.txt
pytest_doctest_only-0.1.2.dist-info/top_level.txt
pytest_doctest_only-0.1.2.dist-info/RECORD
