Metadata-Version: 2.4
Name: pytest-doctest-only
Version: 0.1.2
Summary: A plugin to run only doctest
Author-email: Erez Amihud <erezamihud@gmail.com>
Maintainer-email: Erez Amihud <erezamihud@gmail.com>
License: 
Project-URL: Repository, https://github.com/erezamihud/pytest-doctest-only
Classifier: Framework :: Pytest
Classifier: Development Status :: 4 - Beta
Classifier: Intended Audience :: Developers
Classifier: Topic :: Software Development :: Testing
Classifier: Operating System :: OS Independent
Classifier: Programming Language :: Python
Classifier: Programming Language :: Python :: 3.8
Classifier: Programming Language :: Python :: 3.9
Classifier: Programming Language :: Python :: 3.10
Classifier: Programming Language :: Python :: 3.11
Classifier: Programming Language :: Python :: 3.12
Classifier: Programming Language :: Python :: 3 :: Only
Classifier: Programming Language :: Python :: Implementation :: CPython
Classifier: Programming Language :: Python :: Implementation :: PyPy
Classifier: License :: OSI Approved :: MIT License
Requires-Python: >=3.8
License-File: LICENSE
Requires-Dist: pytest>=8.3.0
Dynamic: license-file
